README.txt
setup.cfg
setup.py
Products/__init__.py
Products.MetaWeblogPASPlugin.egg-info/PKG-INFO
Products.MetaWeblogPASPlugin.egg-info/SOURCES.txt
Products.MetaWeblogPASPlugin.egg-info/dependency_links.txt
Products.MetaWeblogPASPlugin.egg-info/entry_points.txt
Products.MetaWeblogPASPlugin.egg-info/namespace_packages.txt
Products.MetaWeblogPASPlugin.egg-info/not-zip-safe
Products.MetaWeblogPASPlugin.egg-info/requires.txt
Products.MetaWeblogPASPlugin.egg-info/top_level.txt
Products/MetaWeblogPASPlugin/LICENSE.txt
Products/MetaWeblogPASPlugin/README.txt
Products/MetaWeblogPASPlugin/__init__.py
Products/MetaWeblogPASPlugin/config.py
Products/MetaWeblogPASPlugin/pascredentialplugin.py
Products/MetaWeblogPASPlugin/version.txt
Products/MetaWeblogPASPlugin/Extensions/Install.py
Products/MetaWeblogPASPlugin/www/metaweblogAdd.zpt
docs/HISTORY.txt
docs/INSTALL.txt
docs/LICENSE.GPL
docs/LICENSE.txt
