Metadata-Version: 1.0
Name: Products.MetaWeblogPASPlugin
Version: 1.0.0b2
Summary: Enables user authentication for the MetaWeblogAPI
Home-page: http://plone.org/products/quills
Author: Quills Team
Author-email: quills-dev@lists.etria.com
License: GPL
Keywords: plone blogging metaweblog
Platform: UNKNOWN
Classifier: Framework :: Plone
Classifier: Framework :: Zope2
Classifier: Framework :: Zope3
Classifier: Programming Language :: Python
Classifier: Topic :: Software Development :: Libraries :: Python Modules
